gulf_id_scanner/__init__.py
gulf_id_scanner/__main__.py
gulf_id_scanner/client.py
gulf_id_scanner/exceptions.py
gulf_id_scanner/models.py
gulf_id_scanner/tests/__init__.py
gulf_id_scanner-0.1.0b2.dist-info/METADATA
gulf_id_scanner-0.1.0b2.dist-info/WHEEL
gulf_id_scanner-0.1.0b2.dist-info/RECORD
