Metadata-Version: 2.1
Name: gulf-id-scanner
Version: 0.1.0b2
Summary: Python websocket client for reading Gulf IDs
Home-page: https://github.com/Gallagher-ME/gulf_id_scanner
License: MIT
Author: Rami Mousleh
Author-email: engrbm87@gmail.com
Requires-Python: >=3.10,<4.0
Classifier: License :: OSI Approved :: MIT License
Classifier: Programming Language :: Python :: 3
Classifier: Programming Language :: Python :: 3.10
Classifier: Programming Language :: Python :: 3.11
Classifier: Programming Language :: Python :: 3.12
Requires-Dist: aiohttp (>=3.8.4,<4.0.0)
Requires-Dist: orjson (>=3.9.2,<4.0.0)
Requires-Dist: typing-extensions (>=4.7.1,<5.0.0)
Requires-Dist: websockets (>=11.0.3,<12.0.0)
Project-URL: Repository, https://github.com/Gallagher-ME/gulf_id_scanner/releases
